setup.py
vesla_pymvc/__init__.py
vesla_pymvc/utils.py
vesla_pymvc.egg-info/PKG-INFO
vesla_pymvc.egg-info/SOURCES.txt
vesla_pymvc.egg-info/dependency_links.txt
vesla_pymvc.egg-info/not-zip-safe
vesla_pymvc.egg-info/requires.txt
vesla_pymvc.egg-info/top_level.txt
vesla_pymvc/controllers/__init__.py
vesla_pymvc/controllers/controller.py
vesla_pymvc/db/__init__.py
vesla_pymvc/db/db.py
vesla_pymvc/models/__init__.py
vesla_pymvc/models/model.py