Metadata-Version: 2.1
Name: vesla-pymvc
Version: 1.0.0
Summary: Some MVC utils for python projects
Home-page: https://github.com/filipealves/vesla_pymvc
Author: Filipe Alves
Author-email: filipe.alvesdefernando@gmail.com
License: UNKNOWN
Platform: UNKNOWN
